[
  {
    "GuideConditions": [
      {
        "Param": "8002100",
        "Type": "FinishMainMission"
      }
    ],
    "PreConditions": [],
    "ActivityOpenActivityModule": 0,
    "ShopOnlyActivityModule": 0,
    "ActivityGoto": 0,
    "ActivityGotoStoryLineRestore": false,
    "GuideGoto": 0,
    "GuideTakeMission": 0,
    "PanelID": 30006
  },
  {
    "GuideConditions": [
      {
        "Param": "2000701",
        "Type": "FinishMainMission"
      }
    ],
    "PreConditions": [],
    "ActivityOpenActivityModule": 5000102,
    "ShopOnlyActivityModule": 5000108,
    "ActivityGoto": 0,
    "ActivityGotoStoryLineRestore": false,
    "GuideGoto": 0,
    "GuideTakeMission": 0,
    "PanelID": 50001
  },
  {
    "GuideConditions": [],
    "PreConditions": [],
    "ActivityOpenActivityModule": 0,
    "ShopOnlyActivityModule": 0,
    "ActivityGoto": 0,
    "ActivityGotoStoryLineRestore": false,
    "GuideGoto": 0,
    "GuideTakeMission": 0,
    "PanelID": 50003
  },
  {
    "GuideConditions": [
      {
        "Param": "8014101",
        "Type": "FinishMainMission"
      }
    ],
    "PreConditions": [
      {
        "Param": "2010203",
        "Type": "FinishMainMission"
      }
    ],
    "ActivityOpenActivityModule": 0,
    "ShopOnlyActivityModule": 0,
    "ActivityGoto": 0,
    "ActivityGotoStoryLineRestore": false,
    "GuideGoto": 0,
    "GuideTakeMission": 0,
    "PanelID": 50005
  },
  {
    "GuideConditions": [
      {
        "Param": "8015191",
        "Type": "FinishMainMission"
      }
    ],
    "PreConditions": [
      {
        "Param": "1021702",
        "Type": "FinishMainMission"
      }
    ],
    "ActivityOpenActivityModule": 0,
    "ShopOnlyActivityModule": 0,
    "ActivityGoto": 0,
    "ActivityGotoStoryLineRestore": false,
    "GuideGoto": 0,
    "GuideTakeMission": 0,
    "PanelID": 50006
  },
  {
    "GuideConditions": [
      {
        "Param": "8014161",
        "Type": "FinishMainMission"
      }
    ],
    "PreConditions": [
      {
        "Param": "8013103",
        "Type": "FinishMainMission"
      }
    ],
    "ActivityOpenActivityModule": 0,
    "ShopOnlyActivityModule": 0,
    "ActivityGoto": 0,
    "ActivityGotoStoryLineRestore": false,
    "GuideGoto": 0,
    "GuideTakeMission": 0,
    "PanelID": 60006
  },
  {
    "GuideConditions": [
      {
        "Param": "8016201",
        "Type": "FinishMainMission"
      },
      {
        "Param": "8016202",
        "Type": "FinishMainMission"
      },
      {
        "Param": "8016210",
        "Type": "FinishMainMission"
      },
      {
        "Param": "8016203",
        "Type": "FinishMainMission"
      }
    ],
    "PreConditions": [
      {
        "Param": "2001001",
        "Type": "FinishMainMission"
      }
    ],
    "ActivityOpenActivityModule": 0,
    "ShopOnlyActivityModule": 0,
    "ActivityGoto": 0,
    "ActivityGotoStoryLineRestore": false,
    "GuideGoto": 0,
    "GuideTakeMission": 0,
    "PanelID": 30008
  },
  {
    "GuideConditions": [
      {
        "Param": "8002211",
        "Type": "FinishMainMission"
      }
    ],
    "PreConditions": [
      {
        "Param": "1021501",
        "Type": "FinishMainMission"
      }
    ],
    "ActivityOpenActivityModule": 0,
    "ShopOnlyActivityModule": 0,
    "ActivityGoto": 0,
    "ActivityGotoStoryLineRestore": false,
    "GuideGoto": 0,
    "GuideTakeMission": 0,
    "PanelID": 40002
  },
  {
    "GuideConditions": [
      {
        "Param": "8016101",
        "Type": "FinishMainMission"
      }
    ],
    "PreConditions": [
      {
        "Param": "8013101",
        "Type": "FinishMainMission"
      },
      {
        "Param": "8013102",
        "Type": "FinishMainMission"
      },
      {
        "Param": "8013104",
        "Type": "FinishMainMission"
      }
    ],
    "ActivityOpenActivityModule": 0,
    "ShopOnlyActivityModule": 0,
    "ActivityGoto": 0,
    "ActivityGotoStoryLineRestore": false,
    "GuideGoto": 0,
    "GuideTakeMission": 0,
    "PanelID": 60007
  },
  {
    "GuideConditions": [
      {
        "Param": "802340110",
        "Type": "FinishSubMission"
      }
    ],
    "PreConditions": [
      {
        "Param": "4030009",
        "Type": "FinishMainMission"
      },
      {
        "Param": "1034109",
        "Type": "FinishMainMission"
      }
    ],
    "ActivityOpenActivityModule": 0,
    "ShopOnlyActivityModule": 0,
    "ActivityGoto": 845,
    "ActivityGotoStoryLineRestore": false,
    "GuideGoto": 850,
    "GuideTakeMission": 0,
    "PanelID": 60011
  },
  {
    "GuideConditions": [
      {
        "Param": "802640102",
        "Type": "FinishSubMission"
      }
    ],
    "PreConditions": [
      {
        "Param": "8013103",
        "Type": "FinishMainMission"
      }
    ],
    "ActivityOpenActivityModule": 0,
    "ShopOnlyActivityModule": 0,
    "ActivityGoto": 7500,
    "ActivityGotoStoryLineRestore": false,
    "GuideGoto": 6221,
    "GuideTakeMission": 0,
    "PanelID": 60016
  },
  {
    "GuideConditions": [
      {
        "Param": "8016301",
        "Type": "FinishMainMission"
      }
    ],
    "PreConditions": [
      {
        "Param": "1011503",
        "Type": "FinishMainMission"
      }
    ],
    "ActivityOpenActivityModule": 0,
    "ShopOnlyActivityModule": 0,
    "ActivityGoto": 0,
    "ActivityGotoStoryLineRestore": false,
    "GuideGoto": 0,
    "GuideTakeMission": 0,
    "PanelID": 40004
  },
  {
    "GuideConditions": [
      {
        "Param": "801710102",
        "Type": "FinishSubMission"
      }
    ],
    "PreConditions": [
      {
        "Param": "1021501",
        "Type": "FinishMainMission"
      },
      {
        "Param": "3",
        "Type": "WorldLevel"
      }
    ],
    "ActivityOpenActivityModule": 0,
    "ShopOnlyActivityModule": 0,
    "ActivityGoto": 0,
    "ActivityGotoStoryLineRestore": false,
    "GuideGoto": 0,
    "GuideTakeMission": 0,
    "PanelID": 10042
  },
  {
    "GuideConditions": [
      {
        "Param": "8020219",
        "Type": "FinishMainMission"
      }
    ],
    "PreConditions": [
      {
        "Param": "1030501",
        "Type": "FinishMainMission"
      }
    ],
    "ActivityOpenActivityModule": 0,
    "ShopOnlyActivityModule": 0,
    "ActivityGoto": 0,
    "ActivityGotoStoryLineRestore": false,
    "GuideGoto": 0,
    "GuideTakeMission": 0,
    "PanelID": 50007
  },
  {
    "GuideConditions": [
      {
        "Param": "8020300",
        "Type": "FinishMainMission"
      }
    ],
    "PreConditions": [
      {
        "Param": "1030801",
        "Type": "FinishMainMission"
      }
    ],
    "ActivityOpenActivityModule": 0,
    "ShopOnlyActivityModule": 0,
    "ActivityGoto": 0,
    "ActivityGotoStoryLineRestore": false,
    "GuideGoto": 0,
    "GuideTakeMission": 0,
    "PanelID": 40005
  },
  {
    "GuideConditions": [],
    "PreConditions": [
      {
        "Param": "1021702",
        "Type": "FinishMainMission"
      }
    ],
    "ActivityOpenActivityModule": 0,
    "ShopOnlyActivityModule": 0,
    "ActivityGoto": 0,
    "ActivityGotoStoryLineRestore": false,
    "GuideGoto": 0,
    "GuideTakeMission": 0,
    "PanelID": 30010
  },
  {
    "GuideConditions": [
      {
        "Param": "8021201",
        "Type": "FinishMainMission"
      }
    ],
    "PreConditions": [
      {
        "Param": "1011503",
        "Type": "FinishMainMission"
      }
    ],
    "ActivityOpenActivityModule": 0,
    "ShopOnlyActivityModule": 0,
    "ActivityGoto": 0,
    "ActivityGotoStoryLineRestore": false,
    "GuideGoto": 0,
    "GuideTakeMission": 0,
    "PanelID": 50010
  },
  {
    "GuideConditions": [
      {
        "Param": "8022201",
        "Type": "FinishMainMission"
      }
    ],
    "PreConditions": [
      {
        "Param": "1030302",
        "Type": "FinishMainMission"
      }
    ],
    "ActivityOpenActivityModule": 0,
    "ShopOnlyActivityModule": 0,
    "ActivityGoto": 28002,
    "ActivityGotoStoryLineRestore": true,
    "GuideGoto": 6202,
    "GuideTakeMission": 0,
    "PanelID": 50011
  },
  {
    "GuideConditions": [
      {
        "Param": "8022101",
        "Type": "FinishMainMission"
      }
    ],
    "PreConditions": [
      {
        "Param": "1033101",
        "Type": "FinishMainMission"
      }
    ],
    "ActivityOpenActivityModule": 0,
    "ShopOnlyActivityModule": 0,
    "ActivityGoto": 28001,
    "ActivityGotoStoryLineRestore": true,
    "GuideGoto": 6201,
    "GuideTakeMission": 0,
    "PanelID": 50012
  },
  {
    "GuideConditions": [
      {
        "Param": "8021100",
        "Type": "FinishMainMission"
      }
    ],
    "PreConditions": [
      {
        "Param": "1032101",
        "Type": "FinishMainMission"
      }
    ],
    "ActivityOpenActivityModule": 0,
    "ShopOnlyActivityModule": 0,
    "ActivityGoto": 27001,
    "ActivityGotoStoryLineRestore": true,
    "GuideGoto": 6200,
    "GuideTakeMission": 8021100,
    "PanelID": 50009
  },
  {
    "GuideConditions": [
      {
        "Param": "8021301",
        "Type": "FinishMainMission"
      }
    ],
    "PreConditions": [],
    "ActivityOpenActivityModule": 0,
    "ShopOnlyActivityModule": 0,
    "ActivityGoto": 0,
    "ActivityGotoStoryLineRestore": true,
    "GuideGoto": 6203,
    "GuideTakeMission": 0,
    "PanelID": 50008
  },
  {
    "GuideConditions": [
      {
        "Param": "8023101",
        "Type": "FinishMainMission"
      }
    ],
    "PreConditions": [
      {
        "Param": "1034109",
        "Type": "FinishMainMission"
      }
    ],
    "ActivityOpenActivityModule": 0,
    "ShopOnlyActivityModule": 0,
    "ActivityGoto": 29001,
    "ActivityGotoStoryLineRestore": true,
    "GuideGoto": 6205,
    "GuideTakeMission": 8023101,
    "PanelID": 50014
  },
  {
    "GuideConditions": [
      {
        "Param": "8024101",
        "Type": "FinishMainMission"
      }
    ],
    "PreConditions": [
      {
        "Param": "2022101",
        "Type": "FinishMainMission"
      },
      {
        "Param": "2021701",
        "Type": "FinishMainMission"
      },
      {
        "Param": "1021702",
        "Type": "FinishMainMission"
      }
    ],
    "ActivityOpenActivityModule": 0,
    "ShopOnlyActivityModule": 0,
    "ActivityGoto": 29011,
    "ActivityGotoStoryLineRestore": true,
    "GuideGoto": 6208,
    "GuideTakeMission": 8024101,
    "PanelID": 50015
  },
  {
    "GuideConditions": [],
    "PreConditions": [
      {
        "Param": "4020103",
        "Type": "FinishMainMission"
      }
    ],
    "ActivityOpenActivityModule": 0,
    "ShopOnlyActivityModule": 0,
    "ActivityGoto": 0,
    "ActivityGotoStoryLineRestore": false,
    "GuideGoto": 0,
    "GuideTakeMission": 0,
    "PanelID": 10061
  },
  {
    "GuideConditions": [
      {
        "Param": "8023201",
        "Type": "FinishMainMission"
      }
    ],
    "PreConditions": [],
    "ActivityOpenActivityModule": 0,
    "ShopOnlyActivityModule": 0,
    "ActivityGoto": 6700,
    "ActivityGotoStoryLineRestore": false,
    "GuideGoto": 6204,
    "GuideTakeMission": 0,
    "PanelID": 50016
  },
  {
    "GuideConditions": [
      {
        "Param": "8024301",
        "Type": "FinishMainMission"
      }
    ],
    "PreConditions": [
      {
        "Param": "1030302",
        "Type": "FinishMainMission"
      }
    ],
    "ActivityOpenActivityModule": 0,
    "ShopOnlyActivityModule": 0,
    "ActivityGoto": 30001,
    "ActivityGotoStoryLineRestore": true,
    "GuideGoto": 6206,
    "GuideTakeMission": 0,
    "PanelID": 50017
  },
  {
    "GuideConditions": [
      {
        "Param": "8024201",
        "Type": "FinishMainMission"
      }
    ],
    "PreConditions": [
      {
        "Param": "1011503",
        "Type": "FinishMainMission"
      }
    ],
    "ActivityOpenActivityModule": 0,
    "ShopOnlyActivityModule": 0,
    "ActivityGoto": 30015,
    "ActivityGotoStoryLineRestore": true,
    "GuideGoto": 6207,
    "GuideTakeMission": 8024201,
    "PanelID": 50020
  },
  {
    "GuideConditions": [
      {
        "Param": "8025201",
        "Type": "FinishMainMission"
      }
    ],
    "PreConditions": [
      {
        "Param": "2022308",
        "Type": "FinishMainMission"
      },
      {
        "Param": "1021702",
        "Type": "FinishMainMission"
      }
    ],
    "ActivityOpenActivityModule": 0,
    "ShopOnlyActivityModule": 0,
    "ActivityGoto": 33001,
    "ActivityGotoStoryLineRestore": true,
    "GuideGoto": 6210,
    "GuideTakeMission": 0,
    "PanelID": 50021
  },
  {
    "GuideConditions": [
      {
        "Param": "8025101",
        "Type": "FinishMainMission"
      }
    ],
    "PreConditions": [
      {
        "Param": "2022308",
        "Type": "FinishMainMission"
      },
      {
        "Param": "2010203",
        "Type": "FinishMainMission"
      },
      {
        "Param": "1021702",
        "Type": "FinishMainMission"
      }
    ],
    "ActivityOpenActivityModule": 0,
    "ShopOnlyActivityModule": 0,
    "ActivityGoto": 31001,
    "ActivityGotoStoryLineRestore": true,
    "GuideGoto": 6213,
    "GuideTakeMission": 8025101,
    "PanelID": 50018
  },
  {
    "GuideConditions": [
      {
        "Param": "8026101",
        "Type": "FinishMainMission"
      }
    ],
    "PreConditions": [
      {
        "Param": "2001001",
        "Type": "FinishMainMission"
      },
      {
        "Param": "1034210",
        "Type": "FinishMainMission"
      },
      {
        "Param": "1034109",
        "Type": "FinishMainMission"
      }
    ],
    "ActivityOpenActivityModule": 0,
    "ShopOnlyActivityModule": 0,
    "ActivityGoto": 32001,
    "ActivityGotoStoryLineRestore": true,
    "GuideGoto": 6209,
    "GuideTakeMission": 8026101,
    "PanelID": 50022
  },
  {
    "GuideConditions": [
      {
        "Param": "8026201",
        "Type": "FinishMainMission"
      }
    ],
    "PreConditions": [
      {
        "Param": "1011503",
        "Type": "FinishMainMission"
      }
    ],
    "ActivityOpenActivityModule": 0,
    "ShopOnlyActivityModule": 0,
    "ActivityGoto": 34001,
    "ActivityGotoStoryLineRestore": true,
    "GuideGoto": 6211,
    "GuideTakeMission": 8026201,
    "PanelID": 30011
  },
  {
    "GuideConditions": [
      {
        "Param": "8027111",
        "Type": "FinishMainMission"
      }
    ],
    "PreConditions": [],
    "ActivityOpenActivityModule": 0,
    "ShopOnlyActivityModule": 0,
    "ActivityGoto": 29012,
    "ActivityGotoStoryLineRestore": true,
    "GuideGoto": 6218,
    "GuideTakeMission": 8027111,
    "PanelID": 50024
  },
  {
    "GuideConditions": [
      {
        "Param": "8026301",
        "Type": "FinishMainMission"
      }
    ],
    "PreConditions": [
      {
        "Param": "1034210",
        "Type": "FinishMainMission"
      },
      {
        "Param": "1034109",
        "Type": "FinishMainMission"
      }
    ],
    "ActivityOpenActivityModule": 0,
    "ShopOnlyActivityModule": 0,
    "ActivityGoto": 3199,
    "ActivityGotoStoryLineRestore": true,
    "GuideGoto": 6214,
    "GuideTakeMission": 8026301,
    "PanelID": 30012
  },
  {
    "GuideConditions": [
      {
        "Param": "8027200",
        "Type": "FinishMainMission"
      }
    ],
    "PreConditions": [
      {
        "Param": "1034210",
        "Type": "FinishMainMission"
      },
      {
        "Param": "2022308",
        "Type": "FinishMainMission"
      },
      {
        "Param": "1021702",
        "Type": "FinishMainMission"
      },
      {
        "Param": "1034109",
        "Type": "FinishMainMission"
      },
      {
        "Param": "8022402",
        "Type": "FinishMainMission"
      }
    ],
    "ActivityOpenActivityModule": 0,
    "ShopOnlyActivityModule": 0,
    "ActivityGoto": 6220,
    "ActivityGotoStoryLineRestore": true,
    "GuideGoto": 6219,
    "GuideTakeMission": 8027200,
    "PanelID": 50025
  }
]